pyfunclink/__init__.py
pyfunclink/core.py
pyfunclink/html_link.py
pyfunclink/qt_link.py
pyfunclink/tkinter_link.py
pyfunclink/wx_link.py
pyfunclink-1.0.dist-info/METADATA
pyfunclink-1.0.dist-info/WHEEL
pyfunclink-1.0.dist-info/top_level.txt
pyfunclink-1.0.dist-info/RECORD
